Metadata-Version: 2.1
Name: jsonner
Version: 0.1.0
Summary: Python requests extension for JSON-based request information
Classifier: Programming Language :: Python :: 3
Classifier: License :: OSI Approved :: MIT License
Classifier: Operating System :: OS Independent
